README.md
setup.py
jgscm/__init__.py
jgscm.egg-info/PKG-INFO
jgscm.egg-info/SOURCES.txt
jgscm.egg-info/dependency_links.txt
jgscm.egg-info/requires.txt
jgscm.egg-info/top_level.txt