Metadata-Version: 1.1
Name: jgscm
Version: 0.1.9
Summary: Jupyter Google Cloud Storage ContentsManager
Home-page: https://github.com/src-d/jgscm
Author: Vadim Markovtsev
Author-email: vadim@sourced.tech
License: MIT
Download-URL: https://github.com/src-d/jgscm
Keywords: jupyter,ipython,gcloud,gcs
Platform: UNKNOWN
Classifier: Development Status :: 3 - Alpha
Classifier: Intended Audience :: End Users/Desktop
Classifier: License :: OSI Approved :: MIT License
Classifier: Programming Language :: Python :: 2.7
Classifier: Programming Language :: Python :: 3.2
Classifier: Programming Language :: Python :: 3.3
Classifier: Programming Language :: Python :: 3.4
Classifier: Topic :: Software Development :: Libraries
